[
  {
    "query": "在职教师被开除已进入劳动仲裁",
    "display_query": "在职教师被开除已进入劳动仲裁"
  },
  { "query": "新品驾到", "display_query": "新品驾到" },
  { "query": "WBG战胜IG", "display_query": "WBG战胜IG" },
  { "query": "王楚钦3比0户上隼辅", "display_query": "王楚钦3比0户上隼辅" },
  { "query": "正月初十十全十美", "display_query": "正月初十十全十美" },
  { "query": "高考倒计时100天", "display_query": "高考倒计时100天" },
  {
    "query": "乐队打架什么乐器伤害最高",
    "display_query": "乐队打架什么乐器伤害最高"
  },
  {
    "query": "如何用最少的钱打扮自己",
    "display_query": "如何用最少的钱打扮自己"
  },
  { "query": "中餐和西餐哪个油腻", "display_query": "中餐和西餐哪个油腻" },
  { "query": "你的低成本爱好是什么", "display_query": "你的低成本爱好是什么" },
  {
    "query": "古巴与美籍快艇交火 4 死 6 伤",
    "display_query": "古巴与美籍快艇交火 4 死 6 伤"
  },
  {
    "query": "嘴角小水泡别乱处理严重可致命",
    "display_query": "嘴角小水泡别乱处理严重可致命"
  },
  { "query": "四六级成绩公布", "display_query": "四六级成绩公布" },
  { "query": "湖人不敌魔术", "display_query": "湖人不敌魔术" }
]
