[
  { "query": "美联储维持利率不变", "display_query": "美联储维持利率不变" },
  {
    "query": "沪深两市成交额突破5000亿元",
    "display_query": "沪深两市成交额突破5000亿元"
  },
  {
    "query": "美联储宣布维持基准利率不变",
    "display_query": "美联储宣布维持基准利率不变"
  },
  { "query": "如何评价大冰", "display_query": "如何评价大冰" },
  { "query": "湖人vs骑士", "display_query": "湖人vs骑士" },
  { "query": "你们觉得穷游有意义吗", "display_query": "你们觉得穷游有意义吗" },
  {
    "query": "哪些东西已经贵到不值得买了",
    "display_query": "哪些东西已经贵到不值得买了"
  },
  { "query": "中餐和西餐哪个油腻", "display_query": "中餐和西餐哪个油腻" },
  {
    "query": "北方用饺子接待客人是重视吗",
    "display_query": "北方用饺子接待客人是重视吗"
  },
  { "query": "你的低成本爱好是什么", "display_query": "你的低成本爱好是什么" }
]
