[
  { "query": "湖人不敌魔术", "display_query": "湖人不敌魔术" },
  { "query": "酒驾", "display_query": "酒驾" },
  { "query": "退税", "display_query": "退税" },
  { "query": "考研查分", "display_query": "考研查分" },
  { "query": "掘金vs雷霆", "display_query": "掘金vs雷霆" },
  { "query": "男篮世预赛", "display_query": "男篮世预赛" },
  {
    "query": "国内金饰克价突破1600元",
    "display_query": "国内金饰克价突破1600元"
  },
  { "query": "欧冠淘汰赛抽签仪式", "display_query": "欧冠淘汰赛抽签仪式" },
  {
    "query": "生化危机9里昂人设争议",
    "display_query": "生化危机9里昂人设争议"
  },
  { "query": "BLG战胜WBG赛后数据", "display_query": "BLG战胜WBG赛后数据" },
  { "query": "我的春节回忆录", "display_query": "我的春节回忆录" }
]
